[
  {
    "id": "monthly-combo-jan",
    "title": "New Year Grooming Package",
    "description": "Haircut + Beard Trim + Face Massage",
    "discount": "20% off",
    "validUntil": "2024-12-31",
    "services": ["haircut-premium", "beard-trim", "face-massage"],
    "price": 800
  },
  {
    "id": "seasonal-summer",
    "title": "Summer Refresh Package",
    "description": "Face Detan + Hair Wash + Styling",
    "discount": "15% off",
    "validUntil": "2024-12-31",
    "services": ["detan-face", "hair-wash-treatment", "hair-styling"],
    "price": 650
  }
]
